plugins/simulator/verilator_simulator/test_files/netlists/counter/xilinx_unisim_includes/OBUF.v
///////////////////////////////////////////////////////////////////////////////
//    Copyright (c) 1995/2004 Xilinx, Inc.
// 
//    Licensed under the Apache License, Version 2.0 (the "License");
//    you may not use this file except in compliance with the License.
//    You may obtain a copy of the License at
// 
//        http://www.apache.org/licenses/LICENSE-2.0
// 
//    Unless required by applicable law or agreed to in writing, software
//    distributed under the License is distributed on an "AS IS" BASIS,
//    WITHOUT WARRANTIES OR CONDITIONS OF ANY KIND, either express or implied.
//    See the License for the specific language governing permissions and
//    limitations under the License.
///////////////////////////////////////////////////////////////////////////////
//   ____  ____
//  /   /\/   /
// /___/  \  /    Vendor : Xilinx
// \   \   \/     Version : 10.1
//  \   \         Description : Xilinx Functional Simulation Library Component
//  /   /                  Output Buffer
// /___/   /\     Filename : OBUF.v
// \   \  /  \    Timestamp : Thu Mar 25 16:42:59 PST 2004
//  \___\/\___\
//
// Revision:
//    03/23/04 - Initial version.
//    02/22/06 - CR#226003 - Added integer, real parameter type
//    05/23/07 - Changed timescale to 1 ps / 1 ps.

`timescale  1 ps / 1 ps


`celldefine

module OBUF (O, I);

    parameter CAPACITANCE = "DONT_CARE";
    parameter integer DRIVE = 12;
    parameter IOSTANDARD = "DEFAULT";

`ifdef XIL_TIMING

    parameter LOC = " UNPLACED";

`endif

    parameter SLEW = "SLOW";
   
    output O;

    input  I;

    assign O = I;

    
endmodule

`endcelldefine

plugins/simulator/verilator/test_files/netlists/counter/xilinx_unisim_includes/LUT4.v
///////////////////////////////////////////////////////////////////////////////
//    Copyright (c) 1995/2016 Xilinx, Inc.
// 
//    Licensed under the Apache License, Version 2.0 (the "License");
//    you may not use this file except in compliance with the License.
//    You may obtain a copy of the License at
// 
//        http://www.apache.org/licenses/LICENSE-2.0
// 
//    Unless required by applicable law or agreed to in writing, software
//    distributed under the License is distributed on an "AS IS" BASIS,
//    WITHOUT WARRANTIES OR CONDITIONS OF ANY KIND, either express or implied.
//    See the License for the specific language governing permissions and
//    limitations under the License.
///////////////////////////////////////////////////////////////////////////////
//   ____  ____
//  /   /\/   /
// /___/  \  /    Vendor      : Xilinx
// \   \   \/     Version     : 2017.1
//  \   \         Description : Xilinx Unified Simulation Library Component
//  /   /                  4-Bit Look-Up Table
// /___/   /\     Filename : LUT4.v
// \   \  /  \
//  \___\/\___\
//
///////////////////////////////////////////////////////////////////////////////
//  Revision:
//    03/23/04 - Initial version.
//    02/04/05 - Replace primitive with function; Remove buf.
//    03/11/05 - Add LOC Parameter
//    06/04/07 - Add wire declaration to internal signal.
//    12/13/11 - 524859 - Added `celldefine and `endcelldefine
//    09/12/16 - ANSI ports, speed improvements
//  End Revision:
///////////////////////////////////////////////////////////////////////////////

`timescale 1 ps/1 ps

`celldefine

module LUT4 #(
`ifdef XIL_TIMING
  parameter LOC = "UNPLACED",
`endif
  parameter [15:0] INIT = 16'h0000
)(
  output O,

  input I0,
  input I1,
  input I2,
  input I3
);

// define constants
  localparam MODULE_NAME = "LUT4";

  reg trig_attr = 1'b0;
// include dynamic registers - XILINX test only
`ifdef XIL_DR
  `include "LUT4_dr.v"
`else
  reg [15:0] INIT_REG = INIT;
`endif

// begin behavioral model

  reg O_out;

  assign O = O_out;

  function lut_mux4_f;
  input [3:0] d;
  input [1:0] s;
  begin
    if (((s[1]^s[0]) === 1'b1) || ((s[1]^s[0]) === 1'b0))
      lut_mux4_f = d[s];
    else if ( ~(|d) || &d)
      lut_mux4_f = d[0];
    else if (((s[0] === 1'b1) || (s[0] === 1'b0)) && (d[{1'b0,s[0]}] === d[{1'b1,s[0]}]))
      lut_mux4_f = d[{1'b0,s[0]}];
    else if (((s[1] === 1'b1) || (s[1] === 1'b0)) && (d[{s[1],1'b0}] === d[{s[1],1'b1}]))
      lut_mux4_f = d[{s[1],1'b0}];
    else
      lut_mux4_f = 1'bx;
  end
  endfunction

 always @(I0 or I1 or I2 or I3)  begin
   if ( (I0 ^ I1  ^ I2 ^ I3) === 1'b0 || (I0 ^ I1  ^ I2 ^ I3) === 1'b1)
    O_out = INIT_REG[{I3, I2, I1, I0}];
   else if ( ~(|INIT_REG) || &INIT_REG )
    O_out = INIT_REG[0];
   else
    O_out = lut_mux4_f ({lut_mux4_f (INIT_REG[15:12], {I1, I0}),
                     lut_mux4_f ( INIT_REG[11:8], {I1, I0}),
                     lut_mux4_f (  INIT_REG[7:4], {I1, I0}),
                     lut_mux4_f (  INIT_REG[3:0], {I1, I0})}, {I3, I2});
  end

// end behavioral model

`ifdef XIL_TIMING
  specify
	(I0 => O) = (0:0:0, 0:0:0);
	(I1 => O) = (0:0:0, 0:0:0);
	(I2 => O) = (0:0:0, 0:0:0);
	(I3 => O) = (0:0:0, 0:0:0);
	specparam PATHPULSE$ = 0;
  endspecify
`endif

endmodule

`endcelldefine

plugins/simulator/verilator/test_files/netlists/counter/xilinx_unisim_includes/IBUF.v
///////////////////////////////////////////////////////////////////////////////
//    Copyright (c) 1995/2004 Xilinx, Inc.
// 
//    Licensed under the Apache License, Version 2.0 (the "License");
//    you may not use this file except in compliance with the License.
//    You may obtain a copy of the License at
// 
//        http://www.apache.org/licenses/LICENSE-2.0
// 
//    Unless required by applicable law or agreed to in writing, software
//    distributed under the License is distributed on an "AS IS" BASIS,
//    WITHOUT WARRANTIES OR CONDITIONS OF ANY KIND, either express or implied.
//    See the License for the specific language governing permissions and
//    limitations under the License.
///////////////////////////////////////////////////////////////////////////////
//   ____  ____
//  /   /\/   /
// /___/  \  /    Vendor : Xilinx
// \   \   \/     Version : 10.1
//  \   \         Description : Xilinx Functional Simulation Library Component
//  /   /                  Input Buffer
// /___/   /\     Filename : IBUF.v
// \   \  /  \    Timestamp : Thu Mar 25 16:42:23 PST 2004
//  \___\/\___\
//
// Revision:
//    03/23/04 - Initial version.
//    05/23/07 - Changed timescale to 1 ps / 1 ps.
//    07/16/08 - Added IBUF_LOW_PWR attribute.
//    04/22/09 - CR 519127 - Changed IBUF_LOW_PWR default to TRUE.
//    12/13/11 - Added `celldefine and `endcelldefine (CR 524859).
//    10/22/14 - Added #1 to $finish (CR 808642).
// End Revision

`timescale  1 ps / 1 ps


`celldefine

module IBUF (O, I);

    parameter CAPACITANCE = "DONT_CARE";
    parameter IBUF_DELAY_VALUE = "0";
    parameter IBUF_LOW_PWR = "TRUE";
    parameter IFD_DELAY_VALUE = "AUTO";
    parameter IOSTANDARD = "DEFAULT";

`ifdef XIL_TIMING

    parameter LOC = " UNPLACED";

`endif

    
    output O;
    input  I;

    buf B1 (O, I);
    
    
    initial begin
	
        case (CAPACITANCE)

            "LOW", "NORMAL", "DONT_CARE" : ;
            default : begin
                          $display("Attribute Syntax Error : The attribute CAPACITANCE on IBUF instance %m is set to %s.  Legal values for this attribute are DONT_CARE, LOW or NORMAL.", CAPACITANCE);
                          #1 $finish;
                      end

        endcase


	case (IBUF_DELAY_VALUE)

            "0", "1", "2", "3", "4", "5", "6", "7", "8", "9", "10", "11", "12", "13", "14", "15", "16" : ;
            default : begin
                          $display("Attribute Syntax Error : The attribute IBUF_DELAY_VALUE on IBUF instance %m is set to %s.  Legal values for this attribute are 0, 1, 2, ... or 16.", IBUF_DELAY_VALUE);
                          #1 $finish;
                      end

        endcase

        case (IBUF_LOW_PWR)

            "FALSE", "TRUE" : ;
            default : begin
                          $display("Attribute Syntax Error : The attribute IBUF_LOW_PWR on IBUF instance %m is set to %s.  Legal values for this attribute are TRUE or FALSE.", IBUF_LOW_PWR);
                          #1 $finish;
                      end

        endcase


	case (IFD_DELAY_VALUE)

            "AUTO", "0", "1", "2", "3", "4", "5", "6", "7", "8" : ;
            default : begin
                          $display("Attribute Syntax Error : The attribute IFD_DELAY_VALUE on IBUF instance %m is set to %s.  Legal values for this attribute are AUTO, 0, 1, 2, ... or 8.", IFD_DELAY_VALUE);
                          #1 $finish;
                      end

	endcase
	
    end


`ifdef XIL_TIMING
    
    specify
        (I => O) = (0:0:0, 0:0:0);
        specparam PATHPULSE$ = 0;
    endspecify
    
`endif

    
endmodule

`endcelldefine

plugins/simulator/verilator/test_files/netlists/counter/xilinx_unisim_includes/FDCE.v
///////////////////////////////////////////////////////////////////////////////
//    Copyright (c) 1995/2016 Xilinx, Inc.
//
//    Licensed under the Apache License, Version 2.0 (the "License");
//    you may not use this file except in compliance with the License.
//    You may obtain a copy of the License at
//
//        http://www.apache.org/licenses/LICENSE-2.0
//
//    Unless required by applicable law or agreed to in writing, software
//    distributed under the License is distributed on an "AS IS" BASIS,
//    WITHOUT WARRANTIES OR CONDITIONS OF ANY KIND, either express or implied.
//    See the License for the specific language governing permissions and
//    limitations under the License.
///////////////////////////////////////////////////////////////////////////////
//   ____  ____
//  /   /\/   /
// /___/  \  /    Vendor : Xilinx
// \   \   \/     Version : 2017.1
//  \   \         Description : Xilinx Unified Simulation Library Component
//  /   /                  D Flip-Flop with Clock Enable and Asynchronous Clear
// /___/   /\     Filename : FDCE.v
// \   \  /  \
//  \___\/\___\
//
// Revision:
//    08/24/10 - Initial version.
//    10/20/10 - remove unused pin line from table.
//    11/01/11 - Disable timing check when set reset active (CR632017)
//    12/08/11 - add MSGON and XON attributes (CR636891)
//    01/16/12 - 640813 - add MSGON and XON functionality
//    04/16/13 - PR683925 - add invertible pin support.
// End Revision

`timescale  1 ps / 1 ps

`celldefine 

module FDCE #(
           parameter [0:0] INIT = 1'b0
       )(
           output reg Q,

           input C,
           input CE,
           input CLR,
           input D
       );


initial begin
    Q = INIT;
end


always @(posedge C or posedge CLR)
begin
    if(CLR==1'b1)
        Q <= 1'b0;
    else if (CE == 1'b1)
        Q <= D;
    else
        Q <= Q;
end


endmodule

plugins/simulator/verilator/test_files/netlists/counter/xilinx_unisim_includes/INV.v
///////////////////////////////////////////////////////////////////////////////
//    Copyright (c) 1995/2009 Xilinx, Inc.
// 
//    Licensed under the Apache License, Version 2.0 (the "License");
//    you may not use this file except in compliance with the License.
//    You may obtain a copy of the License at
// 
//        http://www.apache.org/licenses/LICENSE-2.0
// 
//    Unless required by applicable law or agreed to in writing, software
//    distributed under the License is distributed on an "AS IS" BASIS,
//    WITHOUT WARRANTIES OR CONDITIONS OF ANY KIND, either express or implied.
//    See the License for the specific language governing permissions and
//    limitations under the License.
///////////////////////////////////////////////////////////////////////////////
//   ____  ____
//  /   /\/   /
// /___/  \  /    Vendor : Xilinx
// \   \   \/     Version : 8.1i (I.13)
//  \   \         Description : Xilinx Timing Simulation Library Component
//  /   /                  Inverter
// /___/   /\     Filename : INV.v
// \   \  /  \    Timestamp : Thu Mar 25 16:43:55 PST 2004
//  \___\/\___\
//
// Revision:
//    03/23/04 - Initial version.
//    03/11/05 - Add LOC paramter;
//    12/13/11 - Added `celldefine and `endcelldefine (CR 524859).
// End Revision

`timescale 1 ps/1 ps

`celldefine

module INV (O, I);


`ifdef XIL_TIMING

  parameter LOC = "UNPLACED";

`endif

  output O;
  input I;

  not n1 (O, I);

`ifdef XIL_TIMING

  specify

	(I => O) = (0:0:0, 0:0:0);
	specparam PATHPULSE$ = 0;

  endspecify

`endif

endmodule

`endcelldefine

plugins/simulator/verilator/test_files/netlists/counter/xilinx_unisim_includes/BUFG.v
///////////////////////////////////////////////////////////////////////////////
//     Copyright (c) 1995/2018 Xilinx, Inc.
// 
//    Licensed under the Apache License, Version 2.0 (the "License");
//    you may not use this file except in compliance with the License.
//    You may obtain a copy of the License at
// 
//        http://www.apache.org/licenses/LICENSE-2.0
// 
//    Unless required by applicable law or agreed to in writing, software
//    distributed under the License is distributed on an "AS IS" BASIS,
//    WITHOUT WARRANTIES OR CONDITIONS OF ANY KIND, either express or implied.
//    See the License for the specific language governing permissions and
//    limitations under the License.
///////////////////////////////////////////////////////////////////////////////
//   ____  ____
//  /   /\/   /
// /___/  \  /     Vendor      : Xilinx
// \   \   \/      Version     : 2018.3
//  \   \          Description : Xilinx Unified Simulation Library Component
//  /   /                        General Clock Buffer
// /___/   /\      Filename    : BUFG.v
// \   \  /  \
//  \___\/\___\
//
///////////////////////////////////////////////////////////////////////////////
//  Revision:
//    03/23/04 - Initial version.
//    05/23/07 - Changed timescale to 1 ps / 1 ps.
//    12/13/11 - 524859 - Added `celldefine and `endcelldefine
//  End Revision:
///////////////////////////////////////////////////////////////////////////////

`timescale 1 ps / 1 ps

`celldefine

module BUFG
`ifdef XIL_TIMING
#(
  parameter LOC = "UNPLACED"
)
`endif
(
  output O,

  input I
);
  
// define constants
  localparam MODULE_NAME = "BUFG";

`ifdef XIL_TIMING
  reg notifier;
`endif

// begin behavioral model

    buf B1 (O, I);

// end behavioral model

`ifndef XIL_XECLIB
`ifdef XIL_TIMING
  specify
    (I => O) = (0:0:0, 0:0:0);
    $period (negedge I, 0:0:0, notifier);
    $period (posedge I, 0:0:0, notifier);
    specparam PATHPULSE$ = 0;
  endspecify
`endif
`endif

endmodule

`endcelldefine

plugins/simulator/verilator_simulator/test/netlists/counter/counter.v
`timescale 1 ps/1 ps

module counter (Reset,Clock_enable_B,Clock,Output_0,Output_3,Output_2,Output_1);
input Reset;
input Clock_enable_B;
input Clock;
output Output_0;
output Output_3;
output Output_2;
output Output_1;
wire temp_2_i_1_n_0;
wire temp_0_i_2_n_0;
wire Clock_enable_B_IBUF;
wire Reset_IBUF;
wire temp_1_i_1_n_0;
wire Output_OBUF_2;
wire Output_OBUF_1;
wire Output_OBUF_3;
wire Output_OBUF_0;
wire Output_OBUF_3;
wire Clock_enable_B_IBUF;
wire Clock_IBUF_BUFG;
wire Clock_IBUF;

LUT4 #(
         .INIT(15'h5A52)
     ) temp_2_i_1_inst (
         .I0(Output_OBUF_3),
         .I1(Output_OBUF_0),
         .I2(Output_OBUF_2),
         .I3(Output_OBUF_1),
         .O(temp_2_i_1_n_0)
     );

FDCE #(
         .INIT(1'b0)
     ) temp_reg_1_inst (
         .C(Clock_IBUF_BUFG),
         .CE(Clock_enable_B_IBUF),
         .CLR(Reset_IBUF),
         .D(temp_1_i_1_n_0),
         .Q(Output_OBUF_1)
     );

FDCE #(
         .INIT(1'b0)
     ) temp_reg_2_inst (
         .C(Clock_IBUF_BUFG),
         .CE(Clock_enable_B_IBUF),
         .CLR(Reset_IBUF),
         .D(temp_2_i_1_n_0),
         .Q(Output_OBUF_2)
     );

IBUF Clock_enable_B_IBUF_inst_inst (
         .I(Clock_enable_B),
         .O(Clock_enable_B_IBUF)
     );

BUFG Clock_IBUF_BUFG_inst_inst (
         .I(Clock_IBUF),
         .O(Clock_IBUF_BUFG)
     );

IBUF Clock_IBUF_inst_inst (
         .I(Clock),
         .O(Clock_IBUF)
     );

INV temp_3_i_1_inst (
        .I(Output_OBUF_3),
        .O(temp_3_i_1_n_0)
    );

FDCE #(
         .INIT(1'b0)
     ) temp_reg_0_inst (
         .C(Clock_IBUF_BUFG),
         .CE(Clock_enable_B_IBUF),
         .CLR(Reset_IBUF),
         .D(temp_0_i_2_n_0),
         .Q(Output_OBUF_0)
     );

OBUF Output_OBUF_3_inst_inst (
         .I(Output_OBUF_3),
         .O(Output_3)
     );


LUT4 #(
         .INIT(16'h7878)
     ) temp_1_i_1_inst (
         .I0(Output_OBUF_3),
         .I1(Output_OBUF_2),
         .I2(Output_OBUF_1),
         .I3(),
         .O(temp_1_i_1_n_0)
     );

FDCE #(
         .INIT(1'b0)
     ) temp_reg_3_inst (
         .C(Clock_IBUF_BUFG),
         .CE(Clock_enable_B_IBUF),
         .CLR(Reset_IBUF),
         .D(temp_3_i_1_n_0),
         .Q(Output_OBUF_3)
     );

IBUF Reset_IBUF_inst_inst (
         .I(Reset),
         .O(Reset_IBUF)
     );

LUT4 #(
         .INIT(15'h6CC4)
     ) temp_0_i_2_inst (
         .I0(Output_OBUF_3),
         .I1(Output_OBUF_0),
         .I2(Output_OBUF_2),
         .I3(Output_OBUF_1),
         .O(temp_0_i_2_n_0)
     );

OBUF Output_OBUF_1_inst_inst (
         .I(Output_OBUF_1),
         .O(Output_1)
     );

OBUF Output_OBUF_0_inst_inst (
         .I(Output_OBUF_0),
         .O(Output_0)
     );

OBUF Output_OBUF_2_inst_inst (
         .I(Output_OBUF_2),
         .O(Output_2)
     );
endmodule

plugins/simulator/verilator_simulator/test/netlists/counter/trace.vcd
$version Generated by VerilatedVcd $end
$date Wed Sep 29 15:10:43 2021 $end
$timescale 1ps $end

 $scope module TOP $end
  $var wire  1 - Clock $end
  $var wire  1 , Clock_enable_B $end
  $var wire  1 . Output_0 $end
  $var wire  1 1 Output_1 $end
  $var wire  1 0 Output_2 $end
  $var wire  1 / Output_3 $end
  $var wire  1 + Reset $end
  $scope module counter $end
   $var wire  1 - Clock $end
   $var wire  1 - Clock_IBUF $end
   $var wire  1 - Clock_IBUF_BUFG $end
   $var wire  1 , Clock_enable_B $end
   $var wire  1 , Clock_enable_B_IBUF $end
   $var wire  1 . Output_0 $end
   $var wire  1 1 Output_1 $end
   $var wire  1 0 Output_2 $end
   $var wire  1 / Output_3 $end
   $var wire  1 ) Output_OBUF_0 $end
   $var wire  1 ' Output_OBUF_1 $end
   $var wire  1 & Output_OBUF_2 $end
   $var wire  1 ( Output_OBUF_3 $end
   $var wire  1 + Reset $end
   $var wire  1 + Reset_IBUF $end
   $var wire  1 $ temp_0_i_2_n_0 $end
   $var wire  1 % temp_1_i_1_n_0 $end
   $var wire  1 # temp_2_i_1_n_0 $end
   $var wire  1 * temp_3_i_1_n_0 $end
  $upscope $end
 $upscope $end
$enddefinitions $end


#8
0#
0$
0%
0&
0'
0(
0)
1*
1+
0,
0-
0.
0/
00
01
#10
1-
#15
0-
#18
0+
#20
1-
#25
0-
#28
1,
#30
1#
1(
0*
1-
1/
#35
0-
#38
#40
1&
0(
1*
1-
0/
10
#45
0-
#48
#50
0#
1%
1(
0*
1-
1/
#55
0-
#58
#60
0&
1'
0(
1*
1-
0/
00
11
#65
0-
#68
#70
1#
1(
0*
1-
1/
#75
0-
#78
0,
#80
1-
#85
0-
#88
#90
1-
#95
0-
#98
0#
0%
0'
0(
1*
1+
0/
01
#100
1-
#105
0-
#108
#110
1-
#115
0-
#118
0+
#120
1-
#125
0-
#128
1,
#130
1#
1(
0*
1-
1/
#135
0-
#138
#140
1&
0(
1*
1-
0/
10
#145
0-
#148
#150
0#
1%
1(
0*
1-
1/
#155
0-
#158
#160
0&
1'
0(
1*
1-
0/
00
11
#165
0-
#168
#170
1#
1(
0*
1-
1/
#175
0-
#178
#180
1&
0(
1*
1-
0/
10
#185
0-
#188
#190
0#
1$
0%
1(
0*
1-
1/
#195
0-
#198
#200
0&
0'
0(
1)
1*
1-
1.
0/
00
01
#205
0-
#208
#210
0$
1(
0*
1-
1/
#215
0-
#218
#220
0(
0)
1*
1-
0.
0/
#225
0-
#228
#230
1#
1(
0*
1-
1/
#235
0-
#238
#240
1&
0(
1*
1-
0/
10
#245
0-
#248
#250
0#
1%
1(
0*
1-
1/
#255
0-
#258
#260
0&
1'
0(
1*
1-
0/
00
11
#265
0-
#268
#270
1#
1(
0*
1-
1/
#275
0-
#278
#280
1&
0(
1*
1-
0/
10
#285
0-
#288
#290
0#
1$
0%
1(
0*
1-
1/
#295
0-
#298
#300
0&
0'
0(
1)
1*
1-
1.
0/
00
01
#305
0-
#308
#310
0$
1(
0*
1-
1/
#315
0-
#318
#320
0(
0)
1*
1-
0.
0/
